ultimate_holdem-0.1.1.dist-info/METADATA
ultimate_holdem-0.1.1.dist-info/WHEEL
ultimate_holdem/__init__.py
ultimate_holdem/ultimate_holdem.cpython-39-darwin.so
ultimate_holdem-0.1.1.dist-info/RECORD
